{
    "TrueZen-nvim": {
        "date": "2022-09-02",
        "new": "true-zen-nvim"
    },
    "compe-tmux": {
        "date": "2021-12-21",
        "new": "cmp-tmux"
    },
    "fern-vim": {
        "date": "2024-05-28",
        "new": "vim-fern"
    },
    "gina-vim": {
        "date": "2024-06-19",
        "new": "vim-gina"
    },
    "gist-vim": {
        "date": "2020-03-27",
        "new": "vim-gist"
    },
    "lspsaga-nvim-original": {
        "date": "2023-08-08",
        "new": "lspsaga-nvim"
    },
    "lua-dev-nvim": {
        "date": "2022-10-20",
        "new": "neodev-nvim"
    },
    "nvchad-extensions": {
        "date": "2023-08-19",
        "new": "nvchad-ui"
    },
    "nvim-base16": {
        "date": "2024-03-16",
        "new": "base16-nvim"
    },
    "nvim-bufferline-lua": {
        "date": "2021-08-22",
        "new": "bufferline-nvim"
    },
    "nvim-lsp": {
        "date": "2020-08-31",
        "new": "nvim-lspconfig"
    },
    "nvim-toggleterm-lua": {
        "date": "2021-08-22",
        "new": "toggleterm-nvim"
    },
    "orgmode-nvim": {
        "date": "2021-11-28",
        "new": "orgmode"
    },
    "sql-nvim": {
        "date": "2021-09-03",
        "new": "sqlite-lua"
    },
    "suda-vim": {
        "date": "2024-05-12",
        "new": "vim-suda"
    },
    "vim-fsharp": {
        "date": "2024-06-19",
        "new": "zarchive-vim-fsharp"
    },
    "vim-jade": {
        "date": "2020-03-27",
        "new": "vim-pug"
    },
    "vundle": {
        "date": "2020-03-27",
        "new": "Vundle-vim"
    },
    "youcompleteme": {
        "date": "2020-03-27",
        "new": "YouCompleteMe"
    }
}
