{
  "version": "0.179.0",
  "binaries": {
    "aarch64-darwin": {
      "url": "https://storage.yandexcloud.net/yandexcloud-yc/release/0.179.0/darwin/arm64/yc",
      "hash": "sha256-fbnGuH+wTSWP6ySYvC//2MVtX/qedq0lpn2NSwod89Q="
    },
    "aarch64-linux": {
      "url": "https://storage.yandexcloud.net/yandexcloud-yc/release/0.179.0/linux/arm64/yc",
      "hash": "sha256-StfGPvi/1H89ox+f1RWK9OyMNMK2u4F1Oinf5yX9hFQ="
    },
    "i686-linux": {
      "url": "https://storage.yandexcloud.net/yandexcloud-yc/release/0.179.0/linux/386/yc",
      "hash": "sha256-7j9iFvaRgsevjwmQdeIosU4ll1wbPufJOpPTDTyXgcU="
    },
    "x86_64-darwin": {
      "url": "https://storage.yandexcloud.net/yandexcloud-yc/release/0.179.0/darwin/amd64/yc",
      "hash": "sha256-CYE374CR735AUx2T2qmTfFnhM/psMwaxHIzHiqhN6d0="
    },
    "x86_64-linux": {
      "url": "https://storage.yandexcloud.net/yandexcloud-yc/release/0.179.0/linux/amd64/yc",
      "hash": "sha256-suxWTcGXsPrwl/2vgVPXPnPI7thD3c4fnZmlgt/pRho="
    }
  }
}
