{
  "version": "0.159.0",
  "binaries": {
    "aarch64-darwin": {
      "url": "https://storage.yandexcloud.net/yandexcloud-yc/release/0.159.0/darwin/arm64/yc",
      "hash": "sha256-T10+afMBPD9vqD/0sG39PVytLjqjO4peB4+ca8vV/i8="
    },
    "aarch64-linux": {
      "url": "https://storage.yandexcloud.net/yandexcloud-yc/release/0.159.0/linux/arm64/yc",
      "hash": "sha256-m0+c7k/k0X5grmejuhomICYtFpeYyJJa6wgdZbdA7B0="
    },
    "i686-linux": {
      "url": "https://storage.yandexcloud.net/yandexcloud-yc/release/0.159.0/linux/386/yc",
      "hash": "sha256-7khhL28QEY2dfQNvVe0K0aG7MVD4ZCaAiOcq0+cot5I="
    },
    "x86_64-darwin": {
      "url": "https://storage.yandexcloud.net/yandexcloud-yc/release/0.159.0/darwin/amd64/yc",
      "hash": "sha256-1JFf/sAU3BNoeFc/NQunh0wplFMda4WbQ1TgpIap3Ts="
    },
    "x86_64-linux": {
      "url": "https://storage.yandexcloud.net/yandexcloud-yc/release/0.159.0/linux/amd64/yc",
      "hash": "sha256-zt8PhgoR/pjQmhIfg/L50/UwNpIAcLpUsqMNYHtZ1Mo="
    }
  }
}
